link_jam_handle/__init__.py
link_jam_handle/allocation.py
link_jam_handle/exchange.py
link_jam_handle/settings.py
link_jam_handle/trades.py
link_jam_handle/user.py
link_jam_handle/data/__init__.py
link_jam_handle/data/data_handler.py
link_jam_handle/data/base_handlers/__init__.py
link_jam_handle/data/base_handlers/aggregate.py
link_jam_handle/data/base_handlers/backtest.py
link_jam_handle/data/base_handlers/live.py
link_jam_handle/data/base_handlers/main.py
link_jam_handle/data/base_handlers/price.py
link_jam_handle/data/base_handlers/runnable.py
link_jam_handle/data/base_handlers/simulated.py
link_jam_handle/data/pricing/__init__.py
link_jam_handle/data/pricing/base.py
link_jam_handle/data/pricing/live.py
link_jam_handle/data/pricing/simulated.py
link_jam_handle/utils/__init__.py
link_jam_handle/utils/auto.py
link_jam_handle/utils/general.py
link_jam_handle/utils/manager.py
link_jam_handle/utils/ordering.py
link_jam_handle/utils/performance.py
link_jam_handle/utils/price_generator.py
link_jam_handle/utils/tiingo_api.py
link_jam_handle/utils/slippage/__init__.py
link_jam_handle/utils/slippage/random_slippage.py
link_jam_handle/utils/slippage/slippage_model.py
link_jam_handle/utils/trades/__init__.py
link_jam_handle/utils/trades/trade.py
link_jam_handle/utils/trades/trade_type.py
link_jam_handle-0.1.1.dist-info/METADATA
link_jam_handle-0.1.1.dist-info/WHEEL
link_jam_handle-0.1.1.dist-info/top_level.txt
link_jam_handle-0.1.1.dist-info/RECORD
